chem_util/__init__.py
chem_util/chem_constants.py
chem_util/io.py
chem_util/math.py
chem_util/units.py
chem_util-0.0.4.dist-info/METADATA
chem_util-0.0.4.dist-info/WHEEL
chem_util-0.0.4.dist-info/top_level.txt
chem_util-0.0.4.dist-info/RECORD
