Metadata-Version: 2.1
Name: chem-util
Version: 0.0.4
Summary: Random Chemistry/Chemical Engineering Utilities
Home-page: https://github.com/dejac001/chem_util
Author: Robert F. De Jaco
Author-email: dejac001@umn.edu
License: UNKNOWN
Platform: UNKNOWN
Requires-Python: >=3.6
